.gitignore
.travis.yml
LICENSE
MANIFEST.in
README.rst
pytest_vscodedebug.py
requirements.txt
setup.py
tox.ini
.vscode/settings.json
pytest_vscodedebug.egg-info/PKG-INFO
pytest_vscodedebug.egg-info/SOURCES.txt
pytest_vscodedebug.egg-info/dependency_links.txt
pytest_vscodedebug.egg-info/entry_points.txt
pytest_vscodedebug.egg-info/requires.txt
pytest_vscodedebug.egg-info/top_level.txt
tests/conftest.py
tests/test_vscodedebug.py