Metadata-Version: 1.2
Name: pytest-vscodedebug
Version: 0.1.0
Summary: A pytest plugin to easily enable debugging tests within Visual Studio Code
Home-page: https://github.com/tmuguet/pytest-vscodedebug
Author: Thomas Muguet
Author-email: hi@tmuguet.me
Maintainer: Thomas Muguet
Maintainer-email: hi@tmuguet.me
License: MIT
Platform: UNKNOWN
Classifier: Development Status :: 4 - Beta
Classifier: Framework :: Pytest
Classifier: Intended Audience :: Developers
Classifier: Topic :: Software Development :: Testing
Classifier: Topic :: Software Development :: Debuggers
Classifier: Programming Language :: Python
Classifier: Programming Language :: Python :: 3
Classifier: Programming Language :: Python :: 3.5
Classifier: Programming Language :: Python :: 3.6
Classifier: Programming Language :: Python :: 3.7
Classifier: Programming Language :: Python :: 3.8
Classifier: Programming Language :: Python :: 3 :: Only
Classifier: Programming Language :: Python :: Implementation :: CPython
Classifier: Programming Language :: Python :: Implementation :: PyPy
Classifier: Operating System :: OS Independent
Classifier: License :: OSI Approved :: MIT License
Requires-Python: >=3.5
